{
  "pins": {
    "flake-compat": {
      "type": "Git",
      "repository": {
        "type": "Git",
        "url": "https://git.lix.systems/lix-project/flake-compat.git"
      },
      "branch": "main",
      "revision": "f7a7752f237bbc59b868058f70cffd3e436b49b7",
      "url": null,
      "hash": "15xb7kn44qria8d6vq8cs1z3ra65y48fwj5yxbf9vf83iwpb65ls"
    },
    "labs": {
      "type": "Git",
      "repository": {
        "type": "Git",
        "url": "https://git.auxolotl.org/auxolotl/labs.git"
      },
      "branch": "main",
      "revision": "5fc4fd1b5cc307e01628a0fae28f3e11714f318b",
      "url": null,
      "hash": "1irqmb4pbl7b0gaa39m5qj977p8xv3vr868h3abqify9n04jr5pj"
    },
    "nixpkgs": {
      "type": "Channel",
      "name": "nixpkgs-unstable",
      "url": "https://releases.nixos.org/nixpkgs/nixpkgs-25.05pre769919.354953266373/nixexprs.tar.xz",
      "hash": "1bms3m4awb09ziis0mhhmrn7kyd66hbiyxndlh9bkgaycmswy77q"
    }
  },
  "version": 3
}